sakatsuku04/__init__.py
sakatsuku04/bit_stream.py
sakatsuku04/crc_ecc.py
sakatsuku04/enc_dec.py
sakatsuku04/error.py
sakatsuku04/game_data_reader.py
sakatsuku04/game_data_view.py
sakatsuku04/main_frame.py
sakatsuku04/memcard_reader.py
sakatsuku04/memcard_view.py
sakatsuku04/models.py
sakatsuku04/readers.py
sakatsuku04/save_reader.py
sakatsuku04/utils.py
sakatsuku04/version.py
sakatsuku04/resource/__init__.py
sakatsuku04/resource/ability.csv
sakatsuku04/resource/ability1.csv
sakatsuku04/resource/ability_jp.csv
sakatsuku04/resource/cn.csv
sakatsuku04/resource/coaches.csv
sakatsuku04/resource/cooperation_type.csv
sakatsuku04/resource/crc_table.bin
sakatsuku04/resource/grow_type.csv
sakatsuku04/resource/players.csv
sakatsuku04/resource/players_green.csv
sakatsuku04/resource/position.csv
sakatsuku04/resource/regions.csv
sakatsuku04/resource/s_boxes.bin
sakatsuku04/resource/scout_ability.csv
sakatsuku04/resource/scouts.csv
sakatsuku04/resource/styles.csv
sakatsuku04/resource/teams.csv
sakatsuku04/resource/tone_type.csv
sakatsuku04-1.0.4.dist-info/METADATA
sakatsuku04-1.0.4.dist-info/WHEEL
sakatsuku04-1.0.4.dist-info/entry_points.txt
sakatsuku04-1.0.4.dist-info/licenses/LICENSE
sakatsuku04-1.0.4.dist-info/RECORD
