Metadata-Version: 2.4
Name: sakatsuku04
Version: 1.0.4
Summary: Opensource game and save editor for J.League Pro Soccer Club o Tsukurou! 04 (PS2).
Project-URL: Homepage, https://github.com/caol64/sakatsuku04
Author-email: Lei <caol64@gmail.com>
License-Expression: MIT
License-File: LICENSE
Classifier: Development Status :: 5 - Production/Stable
Classifier: Environment :: MacOS X :: Cocoa
Classifier: Environment :: Win32 (MS Windows)
Classifier: Environment :: X11 Applications :: GTK
Classifier: Intended Audience :: End Users/Desktop
Classifier: License :: OSI Approved :: MIT License
Classifier: Operating System :: OS Independent
Classifier: Programming Language :: Python :: 3.10
Classifier: Programming Language :: Python :: 3.11
Classifier: Programming Language :: Python :: 3.12
Classifier: Programming Language :: Python :: 3.13
Classifier: Topic :: Multimedia :: Graphics
Classifier: Topic :: Software Development :: User Interfaces
Classifier: Topic :: Utilities
Requires-Python: >=3.13
Requires-Dist: numpy==2.2.2
Requires-Dist: wxpython==4.2.2
Provides-Extra: dev
Requires-Dist: build==1.2.2; extra == 'dev'
Requires-Dist: pyinstaller==6.11.1; extra == 'dev'
Requires-Dist: tomli==2.2.1; extra == 'dev'
